elkomplex/__init__.py
elkomplex/komplex.py
elkomplex-0.1.2.dist-info/LICENSE
elkomplex-0.1.2.dist-info/METADATA
elkomplex-0.1.2.dist-info/WHEEL
elkomplex-0.1.2.dist-info/top_level.txt
elkomplex-0.1.2.dist-info/RECORD
