Metadata-Version: 2.1
Name: elkomplex
Version: 0.1.2
Summary: Toy implementation of a complex datatype
Author-email: EL KHADIRI Yassine <yassineelkhadiri@gmail.com>
Project-URL: Homepage, https://github.com/elkhadiy/elkomplex
Project-URL: Bug Tracker, https://github.com/elkhadiy/elkomplex/issues
Classifier: Programming Language :: Python :: 3
Classifier: License :: OSI Approved :: MIT License
Classifier: Operating System :: OS Independent
Requires-Python: >=3.7
License-File: LICENSE
Provides-Extra: dev
Requires-Dist: mypy ; extra == 'dev'
Requires-Dist: flake8 ; extra == 'dev'
Provides-Extra: test
Requires-Dist: pytest ; extra == 'test'
